ear_analytics_core/__init__.py
ear_analytics_core/console.py
ear_analytics_core/ear_data.py
ear_analytics_core/events.py
ear_analytics_core/io_api.py
ear_analytics_core/logger.py
ear_analytics_core/metrics.py
ear_analytics_core/paraver.py
ear_analytics_core/phases.py
ear_analytics_core/runtime.py
ear_analytics_core/utils.py
ear_analytics_core-5.0.0.dist-info/licenses/LICENSE
ear_analytics_core-5.0.0.dist-info/METADATA
ear_analytics_core-5.0.0.dist-info/WHEEL
ear_analytics_core-5.0.0.dist-info/top_level.txt
ear_analytics_core-5.0.0.dist-info/RECORD
