Metadata-Version: 2.4
Name: ear-analytics-core
Version: 5.0.0
Summary: Core library for EAR analytics and Energy Models.
Author-email: Oriol Vidal <oriol.vidal@eas4dc.com>, Jalal Lakhlili <jalal.lakhlili@eas4dc.com>
License-Expression: EPL-2.0
Keywords: data,hpc,analysis,ear
Classifier: Programming Language :: Python :: 3
License-File: LICENSE
Requires-Dist: numpy
Requires-Dist: pandas[output-formatting,performance,plot]
Requires-Dist: importlib_resources
Requires-Dist: rich
Requires-Dist: pylatex
Requires-Dist: returns
Provides-Extra: docs
Requires-Dist: sphinx; extra == "docs"
Provides-Extra: tests
Requires-Dist: pytest; extra == "tests"
Dynamic: license-file
